README.md
setup.py
abstract_queue/Queue.py
abstract_queue/__init__.py
abstract_queue/exceptions.py
abstract_queue.egg-info/PKG-INFO
abstract_queue.egg-info/SOURCES.txt
abstract_queue.egg-info/dependency_links.txt
abstract_queue.egg-info/requires.txt
abstract_queue.egg-info/top_level.txt